{"code": "rem", "url": "www.eba.europa.eu/eu/fr/xbrl/crr/fws/rem/gl-2014-07/2021-02-28/mod/rem.json", "architecture": "datapoints", "tables": [{"code": "R_01-00", "url": "r_01.00.csv", "architecture": "datapoints", "open_keys": [], "variables": [{"code": "dp435393", "dimensions": {"concept": "eba_met:md103", "eba_dim:BAS": "eba_BA:x1", "eba_dim:CCA": "eba_CA:x2", "eba_dim:MCY": "eba_MC:x276", "unit": "$baseCurrency"}, "attributes": "$decimalsMonetary"}, {"code": "dp435595", "dimensions": {"concept": "eba_met:md103", "eba_dim:BAS": "eba_BA:x17", "eba_dim:CCA": "eba_CA:x2", "eba_dim:TOS": "eba_RP:x64", "eba_dim:TRE": "eba_MC:x916", "unit": "$baseCurrency"}, "attributes": "$decimalsMonetary"}, {"code": "dp435596", "dimensions": {"concept": "eba_met:md103", "eba_dim:BAS": "eba_BA:x17", "eba_dim:CCA": "eba_CA:x2", "eba_dim:TOS": "eba_RP:x64", "eba_dim:TRE": "eba_MC:x411", "unit": "$baseCurrency"}, "attributes": "$decimalsMonetary"}, {"code": "dp435598", "dimensions": {"concept": "eba_met:md103", "eba_dim:BAS": "eba_BA:x17", "eba_dim:CCA": "eba_CA:x2", "eba_dim:TOS": "eba_RP:x65", "eba_dim:TRE": "eba_MC:x916", "unit": "$baseCurrency"}, "attributes": "$decimalsMonetary"}, {"code": "dp435599", "dimensions": {"concept": "eba_met:md103", "eba_dim:BAS": "eba_BA:x17", "eba_dim:CCA": "eba_CA:x2", "eba_dim:TOS": "eba_RP:x65", "eba_dim:TRE": "eba_MC:x411", "unit": "$baseCurrency"}, "attributes": "$decimalsMonetary"}, {"code": "dp435600", "dimensions": {"concept": "eba_met:md103", "eba_dim:BAS": "eba_BA:x17", "eba_dim:CCA": "eba_CA:x2", "eba_dim:TRE": "eba_MC:x916", "eba_dim:TYA": "eba_TA:x5", "unit": "$baseCurrency"}, "attributes": "$decimalsMonetary"}, {"code": "dp435601", "dimensions": {"concept": "eba_met:md103", "eba_dim:BAS": "eba_BA:x17", "eba_dim:CCA": "eba_CA:x2", "eba_dim:TRE": "eba_MC:x916", "eba_dim:TYA": "eba_TA:x29", "unit": "$baseCurrency"}, "attributes": "$decimalsMonetary"}, {"code": "dp435602", "dimensions": {"concept": "eba_met:md103", "eba_dim:BAS": "eba_BA:x17", "eba_dim:CCA": "eba_CA:x2", "eba_dim:TRE": "eba_MC:x916", "eba_dim:TYA": "eba_TA:x125", "unit": "$baseCurrency"}, "attributes": "$decimalsMonetary"}, {"code": "dp435603", "dimensions": {"concept": "eba_met:md103", "eba_dim:BAS": "eba_BA:x17", "eba_dim:CCA": "eba_CA:x2", "eba_dim:TRE": "eba_MC:x916", "eba_dim:TYA": "eba_TA:x126", "unit": "$baseCurrency"}, "attributes": "$decimalsMonetary"}, {"code": "dp435604", "dimensions": {"concept": "eba_met:md103", "eba_dim:BAS": "eba_BA:x17", "eba_dim:CCA": "eba_CA:x2", "eba_dim:TRE": "eba_MC:x916", "eba_dim:TYA": "eba_TA:x127", "unit": "$baseCurrency"}, "attributes": "$decimalsMonetary"}, {"code": "dp435605", "dimensions": {"concept": "eba_met:md103", "eba_dim:BAS": "eba_BA:x17", "eba_dim:CCA": "eba_CA:x2", "eba_dim:TRE": "eba_MC:x916", "eba_dim:TYA": "eba_TA:x128", "unit": "$baseCurrency"}, "attributes": "$decimalsMonetary"}, {"code": "dp435606", "dimensions": {"concept": "eba_met:md103", "eba_dim:BAS": "eba_BA:x17", "eba_dim:CCA": "eba_CA:x2", "eba_dim:TRE": "eba_MC:x411", "eba_dim:TYA": "eba_TA:x5", "unit": "$baseCurrency"}, "attributes": "$decimalsMonetary"}, {"code": "dp435607", "dimensions": {"concept": "eba_met:md103", "eba_dim:BAS": "eba_BA:x17", "eba_dim:CCA": "eba_CA:x2", "eba_dim:TRE": "eba_MC:x411", "eba_dim:TYA": "eba_TA:x29", "unit": "$baseCurrency"}, "attributes": "$decimalsMonetary"}, {"code": "dp435608", "dimensions": {"concept": "eba_met:md103", "eba_dim:BAS": "eba_BA:x17", "eba_dim:CCA": "eba_CA:x2", "eba_dim:TRE": "eba_MC:x411", "eba_dim:TYA": "eba_TA:x125", "unit": "$baseCurrency"}, "attributes": "$decimalsMonetary"}, {"code": "dp435609", "dimensions": {"concept": "eba_met:md103", "eba_dim:BAS": "eba_BA:x17", "eba_dim:CCA": "eba_CA:x2", "eba_dim:TRE": "eba_MC:x411", "eba_dim:TYA": "eba_TA:x126", "unit": "$baseCurrency"}, "attributes": "$decimalsMonetary"}, {"code": "dp435610", "dimensions": {"concept": "eba_met:md103", "eba_dim:BAS": "eba_BA:x17", "eba_dim:CCA": "eba_CA:x2", "eba_dim:TRE": "eba_MC:x411", "eba_dim:TYA": "eba_TA:x127", "unit": "$baseCurrency"}, "attributes": "$decimalsMonetary"}, {"code": "dp435611", "dimensions": {"concept": "eba_met:md103", "eba_dim:BAS": "eba_BA:x17", "eba_dim:CCA": "eba_CA:x2", "eba_dim:TRE": "eba_MC:x411", "eba_dim:TYA": "eba_TA:x128", "unit": "$baseCurrency"}, "attributes": "$decimalsMonetary"}, {"code": "dp438079", "dimensions": {"concept": "eba_met:ii774", "eba_dim:BAS": "eba_BA:x17", "eba_dim:TOS": "eba_RP:x64"}, "attributes": "$decimalsInteger"}, {"code": "dp438080", "dimensions": {"concept": "eba_met:ii774", "eba_dim:BAS": "eba_BA:x17", "eba_dim:TOS": "eba_RP:x65"}, "attributes": "$decimalsInteger"}, {"code": "dp438093", "dimensions": {"concept": "eba_met:ri882", "eba_dim:BAS": "eba_BA:x17", "eba_dim:TYA": "eba_TA:x5"}, "attributes": "$decimalsDecimal"}, {"code": "dp438094", "dimensions": {"concept": "eba_met:ri882", "eba_dim:BAS": "eba_BA:x17", "eba_dim:TYA": "eba_TA:x29"}, "attributes": "$decimalsDecimal"}, {"code": "dp438095", "dimensions": {"concept": "eba_met:ri882", "eba_dim:BAS": "eba_BA:x17", "eba_dim:TYA": "eba_TA:x125"}, "attributes": "$decimalsDecimal"}, {"code": "dp438096", "dimensions": {"concept": "eba_met:ri882", "eba_dim:BAS": "eba_BA:x17", "eba_dim:TYA": "eba_TA:x126"}, "attributes": "$decimalsDecimal"}, {"code": "dp438097", "dimensions": {"concept": "eba_met:ri882", "eba_dim:BAS": "eba_BA:x17", "eba_dim:TYA": "eba_TA:x127"}, "attributes": "$decimalsDecimal"}, {"code": "dp438098", "dimensions": {"concept": "eba_met:ri882", "eba_dim:BAS": "eba_BA:x17", "eba_dim:TYA": "eba_TA:x128"}, "attributes": "$decimalsDecimal"}], "attributes": []}, {"code": "R_02-00-a", "url": "r_02.00.a.csv", "architecture": "datapoints", "open_keys": [], "variables": [{"code": "dp435325", "dimensions": {"concept": "eba_met:md103", "eba_dim:BAS": "eba_BA:x3", "eba_dim:CCA": "eba_CA:x2", "eba_dim:MCV": "eba_MC:x912", "eba_dim:MCY": "eba_MC:x22", "eba_dim:TIT": "eba_RP:x87", "eba_dim:TYA": "eba_TA:x5", "unit": "$baseCurrency"}, "attributes": "$decimalsMonetary"}, {"code": "dp435326", "dimensions": {"concept": "eba_met:md103", "eba_dim:BAS": "eba_BA:x3", "eba_dim:CCA": "eba_CA:x2", "eba_dim:MCV": "eba_MC:x912", "eba_dim:MCY": "eba_MC:x22", "eba_dim:TIT": "eba_RP:x87", "eba_dim:TYA": "eba_TA:x29", "unit": "$baseCurrency"}, "attributes": "$decimalsMonetary"}, {"code": "dp435327", "dimensions": {"concept": "eba_met:md103", "eba_dim:BAS": "eba_BA:x3", "eba_dim:CCA": "eba_CA:x2", "eba_dim:MCV": "eba_MC:x912", "eba_dim:MCY": "eba_MC:x22", "eba_dim:TIT": "eba_RP:x87", "eba_dim:TYA": "eba_TA:x125", "unit": "$baseCurrency"}, "attributes": "$decimalsMonetary"}, {"code": "dp435328", "dimensions": {"concept": "eba_met:md103", "eba_dim:BAS": "eba_BA:x3", "eba_dim:CCA": "eba_CA:x2", "eba_dim:MCV": "eba_MC:x912", "eba_dim:MCY": "eba_MC:x22", "eba_dim:TIT": "eba_RP:x87", "eba_dim:TYA": "eba_TA:x126", "unit": "$baseCurrency"}, "attributes": "$decimalsMonetary"}, {"code": "dp435329", "dimensions": {"concept": "eba_met:md103", "eba_dim:BAS": "eba_BA:x3", "eba_dim:CCA": "eba_CA:x2", "eba_dim:MCV": "eba_MC:x912", "eba_dim:MCY": "eba_MC:x22", "eba_dim:TIT": "eba_RP:x87", "eba_dim:TYA": "eba_TA:x127", "unit": "$baseCurrency"}, "attributes": "$decimalsMonetary"}, {"code": "dp435330", "dimensions": {"concept": "eba_met:md103", "eba_dim:BAS": "eba_BA:x3", "eba_dim:CCA": "eba_CA:x2", "eba_dim:MCV": "eba_MC:x912", "eba_dim:MCY": "eba_MC:x22", "eba_dim:TIT": "eba_RP:x87", "eba_dim:TYA": "eba_TA:x128", "unit": "$baseCurrency"}, "attributes": "$decimalsMonetary"}, {"code": "dp435331", "dimensions": {"concept": "eba_met:md103", "eba_dim:BAS": "eba_BA:x3", "eba_dim:CCA": "eba_CA:x2", "eba_dim:MCV": "eba_MC:x912", "eba_dim:MCY": "eba_MC:x22", "eba_dim:TIT": "eba_RP:x64", "unit": "$baseCurrency"}, "attributes": "$decimalsMonetary"}, {"code": "dp435332", "dimensions": {"concept": "eba_met:md103", "eba_dim:BAS": "eba_BA:x3", "eba_dim:CCA": "eba_CA:x2", "eba_dim:MCV": "eba_MC:x912", "eba_dim:MCY": "eba_MC:x22", "eba_dim:TIT": "eba_RP:x65", "unit": "$baseCurrency"}, "attributes": "$decimalsMonetary"}, {"code": "dp435333", "dimensions": {"concept": "eba_met:md103", "eba_dim:BAS": "eba_BA:x3", "eba_dim:CCA": "eba_CA:x2", "eba_dim:MCV": "eba_MC:x436", "eba_dim:MCY": "eba_MC:x22", "eba_dim:TIT": "eba_RP:x87", "eba_dim:TYA": "eba_TA:x5", "unit": "$baseCurrency"}, "attributes": "$decimalsMonetary"}, {"code": "dp435334", "dimensions": {"concept": "eba_met:md103", "eba_dim:BAS": "eba_BA:x3", "eba_dim:CCA": "eba_CA:x2", "eba_dim:MCV": "eba_MC:x436", "eba_dim:MCY": "eba_MC:x22", "eba_dim:TIT": "eba_RP:x87", "eba_dim:TYA": "eba_TA:x29", "unit": "$baseCurrency"}, "attributes": "$decimalsMonetary"}, {"code": "dp435335", "dimensions": {"concept": "eba_met:md103", "eba_dim:BAS": "eba_BA:x3", "eba_dim:CCA": "eba_CA:x2", "eba_dim:MCV": "eba_MC:x436", "eba_dim:MCY": "eba_MC:x22", "eba_dim:TIT": "eba_RP:x87", "eba_dim:TYA": "eba_TA:x125", "unit": "$baseCurrency"}, "attributes": "$decimalsMonetary"}, {"code": "dp435336", "dimensions": {"concept": "eba_met:md103", "eba_dim:BAS": "eba_BA:x3", "eba_dim:CCA": "eba_CA:x2", "eba_dim:MCV": "eba_MC:x436", "eba_dim:MCY": "eba_MC:x22", "eba_dim:TIT": "eba_RP:x87", "eba_dim:TYA": "eba_TA:x126", "unit": "$baseCurrency"}, "attributes": "$decimalsMonetary"}, {"code": "dp435337", "dimensions": {"concept": "eba_met:md103", "eba_dim:BAS": "eba_BA:x3", "eba_dim:CCA": "eba_CA:x2", "eba_dim:MCV": "eba_MC:x436", "eba_dim:MCY": "eba_MC:x22", "eba_dim:TIT": "eba_RP:x87", "eba_dim:TYA": "eba_TA:x127", "unit": "$baseCurrency"}, "attributes": "$decimalsMonetary"}, {"code": "dp435338", "dimensions": {"concept": "eba_met:md103", "eba_dim:BAS": "eba_BA:x3", "eba_dim:CCA": "eba_CA:x2", "eba_dim:MCV": "eba_MC:x436", "eba_dim:MCY": "eba_MC:x22", "eba_dim:TIT": "eba_RP:x87", "eba_dim:TYA": "eba_TA:x128", "unit": "$baseCurrency"}, "attributes": "$decimalsMonetary"}, {"code": "dp435339", "dimensions": {"concept": "eba_met:md103", "eba_dim:BAS": "eba_BA:x3", "eba_dim:CCA": "eba_CA:x2", "eba_dim:MCV": "eba_MC:x436", "eba_dim:MCY": "eba_MC:x22", "eba_dim:TIT": "eba_RP:x64", "unit": "$baseCurrency"}, "attributes": "$decimalsMonetary"}, {"code": "dp435340", "dimensions": {"concept": "eba_met:md103", "eba_dim:BAS": "eba_BA:x3", "eba_dim:CCA": "eba_CA:x2", "eba_dim:MCV": "eba_MC:x436", "eba_dim:MCY": "eba_MC:x22", "eba_dim:TIT": "eba_RP:x65", "unit": "$baseCurrency"}, "attributes": "$decimalsMonetary"}, {"code": "dp435341", "dimensions": {"concept": "eba_met:md103", "eba_dim:BAS": "eba_BA:x3", "eba_dim:CCA": "eba_CA:x2", "eba_dim:MCY": "eba_MC:x22", "eba_dim:TIT": "eba_RP:x87", "eba_dim:TRE": "eba_MC:x435", "eba_dim:TYA": "eba_TA:x5", "unit": "$baseCurrency"}, "attributes": "$decimalsMonetary"}, {"code": "dp435342", "dimensions": {"concept": "eba_met:md103", "eba_dim:BAS": "eba_BA:x3", "eba_dim:CCA": "eba_CA:x2", "eba_dim:MCY": "eba_MC:x22", "eba_dim:TIT": "eba_RP:x87", "eba_dim:TRE": "eba_MC:x435", "eba_dim:TYA": "eba_TA:x29", "unit": "$baseCurrency"}, "attributes": "$decimalsMonetary"}, {"code": "dp435343", "dimensions": {"concept": "eba_met:md103", "eba_dim:BAS": "eba_BA:x3", "eba_dim:CCA": "eba_CA:x2", "eba_dim:MCY": "eba_MC:x22", "eba_dim:TIT": "eba_RP:x87", "eba_dim:TRE": "eba_MC:x435", "eba_dim:TYA": "eba_TA:x125", "unit": "$baseCurrency"}, "attributes": "$decimalsMonetary"}, {"code": "dp435344", "dimensions": {"concept": "eba_met:md103", "eba_dim:BAS": "eba_BA:x3", "eba_dim:CCA": "eba_CA:x2", "eba_dim:MCY": "eba_MC:x22", "eba_dim:TIT": "eba_RP:x87", "eba_dim:TRE": "eba_MC:x435", "eba_dim:TYA": "eba_TA:x126", "unit": "$baseCurrency"}, "attributes": "$decimalsMonetary"}, {"code": "dp435345", "dimensions": {"concept": "eba_met:md103", "eba_dim:BAS": "eba_BA:x3", "eba_dim:CCA": "eba_CA:x2", "eba_dim:MCY": "eba_MC:x22", "eba_dim:TIT": "eba_RP:x87", "eba_dim:TRE": "eba_MC:x435", "eba_dim:TYA": "eba_TA:x127", "unit": "$baseCurrency"}, "attributes": "$decimalsMonetary"}, {"code": "dp435346", "dimensions": {"concept": "eba_met:md103", "eba_dim:BAS": "eba_BA:x3", "eba_dim:CCA": "eba_CA:x2", "eba_dim:MCY": "eba_MC:x22", "eba_dim:TIT": "eba_RP:x87", "eba_dim:TRE": "eba_MC:x435", "eba_dim:TYA": "eba_TA:x128", "unit": "$baseCurrency"}, "attributes": "$decimalsMonetary"}, {"code": "dp435347", "dimensions": {"concept": "eba_met:md103", "eba_dim:BAS": "eba_BA:x3", "eba_dim:CCA": "eba_CA:x2", "eba_dim:MCY": "eba_MC:x22", "eba_dim:TIT": "eba_RP:x64", "eba_dim:TRE": "eba_MC:x435", "unit": "$baseCurrency"}, "attributes": "$decimalsMonetary"}, {"code": "dp435348", "dimensions": {"concept": "eba_met:md103", "eba_dim:BAS": "eba_BA:x3", "eba_dim:CCA": "eba_CA:x2", "eba_dim:MCY": "eba_MC:x22", "eba_dim:TIT": "eba_RP:x65", "eba_dim:TRE": "eba_MC:x435", "unit": "$baseCurrency"}, "attributes": "$decimalsMonetary"}, {"code": "dp435462", "dimensions": {"concept": "eba_met:md103", "eba_dim:BAS": "eba_BA:x17", "eba_dim:CCA": "eba_CA:x2", "eba_dim:FRM": "eba_MC:x412", "eba_dim:TIT": "eba_RP:x87", "eba_dim:TRE": "eba_MC:x915", "eba_dim:TYA": "eba_TA:x5", "unit": "$baseCurrency"}, "attributes": "$decimalsMonetary"}, {"code": "dp435463", "dimensions": {"concept": "eba_met:md103", "eba_dim:BAS": "eba_BA:x17", "eba_dim:CCA": "eba_CA:x2", "eba_dim:FRM": "eba_MC:x412", "eba_dim:TIT": "eba_RP:x87", "eba_dim:TRE": "eba_MC:x915", "eba_dim:TYA": "eba_TA:x29", "unit": "$baseCurrency"}, "attributes": "$decimalsMonetary"}, {"code": "dp435464", "dimensions": {"concept": "eba_met:md103", "eba_dim:BAS": "eba_BA:x17", "eba_dim:CCA": "eba_CA:x2", "eba_dim:FRM": "eba_MC:x412", "eba_dim:TIT": "eba_RP:x87", "eba_dim:TRE": "eba_MC:x915", "eba_dim:TYA": "eba_TA:x125", "unit": "$baseCurrency"}, "attributes": "$decimalsMonetary"}, {"code": "dp435465", "dimensions": {"concept": "eba_met:md103", "eba_dim:BAS": "eba_BA:x17", "eba_dim:CCA": "eba_CA:x2", "eba_dim:FRM": "eba_MC:x412", "eba_dim:TIT": "eba_RP:x87", "eba_dim:TRE": "eba_MC:x915", "eba_dim:TYA": "eba_TA:x126", "unit": "$baseCurrency"}, "attributes": "$decimalsMonetary"}, {"code": "dp435466", "dimensions": {"concept": "eba_met:md103", "eba_dim:BAS": "eba_BA:x17", "eba_dim:CCA": "eba_CA:x2", "eba_dim:FRM": "eba_MC:x412", "eba_dim:TIT": "eba_RP:x87", "eba_dim:TRE": "eba_MC:x915", "eba_dim:TYA": "eba_TA:x127", "unit": "$baseCurrency"}, "attributes": "$decimalsMonetary"}, {"code": "dp435467", "dimensions": {"concept": "eba_met:md103", "eba_dim:BAS": "eba_BA:x17", "eba_dim:CCA": "eba_CA:x2", "eba_dim:FRM": "eba_MC:x412", "eba_dim:TIT": "eba_RP:x87", "eba_dim:TRE": "eba_MC:x915", "eba_dim:TYA": "eba_TA:x128", "unit": "$baseCurrency"}, "attributes": "$decimalsMonetary"}, {"code": "dp435468", "dimensions": {"concept": "eba_met:md103", "eba_dim:BAS": "eba_BA:x17", "eba_dim:CCA": "eba_CA:x2", "eba_dim:FRM": "eba_MC:x412", "eba_dim:TIT": "eba_RP:x87", "eba_dim:TRE": "eba_MC:x916", "eba_dim:TYA": "eba_TA:x5", "unit": "$baseCurrency"}, "attributes": "$decimalsMonetary"}, {"code": "dp435469", "dimensions": {"concept": "eba_met:md103", "eba_dim:BAS": "eba_BA:x17", "eba_dim:CCA": "eba_CA:x2", "eba_dim:FRM": "eba_MC:x412", "eba_dim:TIT": "eba_RP:x87", "eba_dim:TRE": "eba_MC:x916", "eba_dim:TYA": "eba_TA:x29", "unit": "$baseCurrency"}, "attributes": "$decimalsMonetary"}, {"code": "dp435470", "dimensions": {"concept": "eba_met:md103", "eba_dim:BAS": "eba_BA:x17", "eba_dim:CCA": "eba_CA:x2", "eba_dim:FRM": "eba_MC:x412", "eba_dim:TIT": "eba_RP:x87", "eba_dim:TRE": "eba_MC:x916", "eba_dim:TYA": "eba_TA:x125", "unit": "$baseCurrency"}, "attributes": "$decimalsMonetary"}, {"code": "dp435471", "dimensions": {"concept": "eba_met:md103", "eba_dim:BAS": "eba_BA:x17", "eba_dim:CCA": "eba_CA:x2", "eba_dim:FRM": "eba_MC:x412", "eba_dim:TIT": "eba_RP:x87", "eba_dim:TRE": "eba_MC:x916", "eba_dim:TYA": "eba_TA:x126", "unit": "$baseCurrency"}, "attributes": "$decimalsMonetary"}, {"code": "dp435472", "dimensions": {"concept": "eba_met:md103", "eba_dim:BAS": "eba_BA:x17", "eba_dim:CCA": "eba_CA:x2", "eba_dim:FRM": "eba_MC:x412", "eba_dim:TIT": "eba_RP:x87", "eba_dim:TRE": "eba_MC:x916", "eba_dim:TYA": "eba_TA:x127", "unit": "$baseCurrency"}, "attributes": "$decimalsMonetary"}, {"code": "dp435473", "dimensions": {"concept": "eba_met:md103", "eba_dim:BAS": "eba_BA:x17", "eba_dim:CCA": "eba_CA:x2", "eba_dim:FRM": "eba_MC:x412", "eba_dim:TIT": "eba_RP:x87", "eba_dim:TRE": "eba_MC:x916", "eba_dim:TYA": "eba_TA:x128", "unit": "$baseCurrency"}, "attributes": "$decimalsMonetary"}, {"code": "dp435474", "dimensions": {"concept": "eba_met:md103", "eba_dim:BAS": "eba_BA:x17", "eba_dim:CCA": "eba_CA:x2", "eba_dim:FRM": "eba_MC:x412", "eba_dim:TIT": "eba_RP:x64", "eba_dim:TRE": "eba_MC:x915", "unit": "$baseCurrency"}, "attributes": "$decimalsMonetary"}, {"code": "dp435475", "dimensions": {"concept": "eba_met:md103", "eba_dim:BAS": "eba_BA:x17", "eba_dim:CCA": "eba_CA:x2", "eba_dim:FRM": "eba_MC:x412", "eba_dim:TIT": "eba_RP:x64", "eba_dim:TRE": "eba_MC:x916", "unit": "$baseCurrency"}, "attributes": "$decimalsMonetary"}, {"code": "dp435476", "dimensions": {"concept": "eba_met:md103", "eba_dim:BAS": "eba_BA:x17", "eba_dim:CCA": "eba_CA:x2", "eba_dim:FRM": "eba_MC:x412", "eba_dim:TIT": "eba_RP:x65", "eba_dim:TRE": "eba_MC:x915", "unit": "$baseCurrency"}, "attributes": "$decimalsMonetary"}, {"code": "dp435477", "dimensions": {"concept": "eba_met:md103", "eba_dim:BAS": "eba_BA:x17", "eba_dim:CCA": "eba_CA:x2", "eba_dim:FRM": "eba_MC:x412", "eba_dim:TIT": "eba_RP:x65", "eba_dim:TRE": "eba_MC:x916", "unit": "$baseCurrency"}, "attributes": "$decimalsMonetary"}, {"code": "dp435494", "dimensions": {"concept": "eba_met:md103", "eba_dim:BAS": "eba_BA:x17", "eba_dim:CCA": "eba_CA:x2", "eba_dim:FRM": "eba_MC:x417", "eba_dim:TIT": "eba_RP:x87", "eba_dim:TRE": "eba_MC:x915", "eba_dim:TYA": "eba_TA:x5", "unit": "$baseCurrency"}, "attributes": "$decimalsMonetary"}, {"code": "dp435495", "dimensions": {"concept": "eba_met:md103", "eba_dim:BAS": "eba_BA:x17", "eba_dim:CCA": "eba_CA:x2", "eba_dim:FRM": "eba_MC:x417", "eba_dim:TIT": "eba_RP:x87", "eba_dim:TRE": "eba_MC:x915", "eba_dim:TYA": "eba_TA:x29", "unit": "$baseCurrency"}, "attributes": "$decimalsMonetary"}, {"code": "dp435496", "dimensions": {"concept": "eba_met:md103", "eba_dim:BAS": "eba_BA:x17", "eba_dim:CCA": "eba_CA:x2", "eba_dim:FRM": "eba_MC:x417", "eba_dim:TIT": "eba_RP:x87", "eba_dim:TRE": "eba_MC:x915", "eba_dim:TYA": "eba_TA:x125", "unit": "$baseCurrency"}, "attributes": "$decimalsMonetary"}, {"code": "dp435497", "dimensions": {"concept": "eba_met:md103", "eba_dim:BAS": "eba_BA:x17", "eba_dim:CCA": "eba_CA:x2", "eba_dim:FRM": "eba_MC:x417", "eba_dim:TIT": "eba_RP:x87", "eba_dim:TRE": "eba_MC:x915", "eba_dim:TYA": "eba_TA:x126", "unit": "$baseCurrency"}, "attributes": "$decimalsMonetary"}, {"code": "dp435498", "dimensions": {"concept": "eba_met:md103", "eba_dim:BAS": "eba_BA:x17", "eba_dim:CCA": "eba_CA:x2", "eba_dim:FRM": "eba_MC:x417", "eba_dim:TIT": "eba_RP:x87", "eba_dim:TRE": "eba_MC:x915", "eba_dim:TYA": "eba_TA:x127", "unit": "$baseCurrency"}, "attributes": "$decimalsMonetary"}, {"code": "dp435499", "dimensions": {"concept": "eba_met:md103", "eba_dim:BAS": "eba_BA:x17", "eba_dim:CCA": "eba_CA:x2", "eba_dim:FRM": "eba_MC:x417", "eba_dim:TIT": "eba_RP:x87", "eba_dim:TRE": "eba_MC:x915", "eba_dim:TYA": "eba_TA:x128", "unit": "$baseCurrency"}, "attributes": "$decimalsMonetary"}, {"code": "dp435500", "dimensions": {"concept": "eba_met:md103", "eba_dim:BAS": "eba_BA:x17", "eba_dim:CCA": "eba_CA:x2", "eba_dim:FRM": "eba_MC:x417", "eba_dim:TIT": "eba_RP:x87", "eba_dim:TRE": "eba_MC:x916", "eba_dim:TYA": "eba_TA:x5", "unit": "$baseCurrency"}, "attributes": "$decimalsMonetary"}, {"code": "dp435501", "dimensions": {"concept": "eba_met:md103", "eba_dim:BAS": "eba_BA:x17", "eba_dim:CCA": "eba_CA:x2", "eba_dim:FRM": "eba_MC:x417", "eba_dim:TIT": "eba_RP:x87", "eba_dim:TRE": "eba_MC:x916", "eba_dim:TYA": "eba_TA:x29", "unit": "$baseCurrency"}, "attributes": "$decimalsMonetary"}, {"code": "dp435502", "dimensions": {"concept": "eba_met:md103", "eba_dim:BAS": "eba_BA:x17", "eba_dim:CCA": "eba_CA:x2", "eba_dim:FRM": "eba_MC:x417", "eba_dim:TIT": "eba_RP:x87", "eba_dim:TRE": "eba_MC:x916", "eba_dim:TYA": "eba_TA:x125", "unit": "$baseCurrency"}, "attributes": "$decimalsMonetary"}, {"code": "dp435503", "dimensions": {"concept": "eba_met:md103", "eba_dim:BAS": "eba_BA:x17", "eba_dim:CCA": "eba_CA:x2", "eba_dim:FRM": "eba_MC:x417", "eba_dim:TIT": "eba_RP:x87", "eba_dim:TRE": "eba_MC:x916", "eba_dim:TYA": "eba_TA:x126", "unit": "$baseCurrency"}, "attributes": "$decimalsMonetary"}, {"code": "dp435504", "dimensions": {"concept": "eba_met:md103", "eba_dim:BAS": "eba_BA:x17", "eba_dim:CCA": "eba_CA:x2", "eba_dim:FRM": "eba_MC:x417", "eba_dim:TIT": "eba_RP:x87", "eba_dim:TRE": "eba_MC:x916", "eba_dim:TYA": "eba_TA:x127", "unit": "$baseCurrency"}, "attributes": "$decimalsMonetary"}, {"code": "dp435505", "dimensions": {"concept": "eba_met:md103", "eba_dim:BAS": "eba_BA:x17", "eba_dim:CCA": "eba_CA:x2", "eba_dim:FRM": "eba_MC:x417", "eba_dim:TIT": "eba_RP:x87", "eba_dim:TRE": "eba_MC:x916", "eba_dim:TYA": "eba_TA:x128", "unit": "$baseCurrency"}, "attributes": "$decimalsMonetary"}, {"code": "dp435506", "dimensions": {"concept": "eba_met:md103", "eba_dim:BAS": "eba_BA:x17", "eba_dim:CCA": "eba_CA:x2", "eba_dim:FRM": "eba_MC:x417", "eba_dim:TIT": "eba_RP:x64", "eba_dim:TRE": "eba_MC:x915", "unit": "$baseCurrency"}, "attributes": "$decimalsMonetary"}, {"code": "dp435507", "dimensions": {"concept": "eba_met:md103", "eba_dim:BAS": "eba_BA:x17", "eba_dim:CCA": "eba_CA:x2", "eba_dim:FRM": "eba_MC:x417", "eba_dim:TIT": "eba_RP:x64", "eba_dim:TRE": "eba_MC:x916", "unit": "$baseCurrency"}, "attributes": "$decimalsMonetary"}, {"code": "dp435508", "dimensions": {"concept": "eba_met:md103", "eba_dim:BAS": "eba_BA:x17", "eba_dim:CCA": "eba_CA:x2", "eba_dim:FRM": "eba_MC:x417", "eba_dim:TIT": "eba_RP:x65", "eba_dim:TRE": "eba_MC:x915", "unit": "$baseCurrency"}, "attributes": "$decimalsMonetary"}, {"code": "dp435509", "dimensions": {"concept": "eba_met:md103", "eba_dim:BAS": "eba_BA:x17", "eba_dim:CCA": "eba_CA:x2", "eba_dim:FRM": "eba_MC:x417", "eba_dim:TIT": "eba_RP:x65", "eba_dim:TRE": "eba_MC:x916", "unit": "$baseCurrency"}, "attributes": "$decimalsMonetary"}, {"code": "dp435526", "dimensions": {"concept": "eba_met:md103", "eba_dim:BAS": "eba_BA:x17", "eba_dim:CCA": "eba_CA:x2", "eba_dim:FRM": "eba_MC:x424", "eba_dim:TIT": "eba_RP:x87", "eba_dim:TRE": "eba_MC:x915", "eba_dim:TYA": "eba_TA:x5", "unit": "$baseCurrency"}, "attributes": "$decimalsMonetary"}, {"code": "dp435527", "dimensions": {"concept": "eba_met:md103", "eba_dim:BAS": "eba_BA:x17", "eba_dim:CCA": "eba_CA:x2", "eba_dim:FRM": "eba_MC:x424", "eba_dim:TIT": "eba_RP:x87", "eba_dim:TRE": "eba_MC:x915", "eba_dim:TYA": "eba_TA:x29", "unit": "$baseCurrency"}, "attributes": "$decimalsMonetary"}, {"code": "dp435528", "dimensions": {"concept": "eba_met:md103", "eba_dim:BAS": "eba_BA:x17", "eba_dim:CCA": "eba_CA:x2", "eba_dim:FRM": "eba_MC:x424", "eba_dim:TIT": "eba_RP:x87", "eba_dim:TRE": "eba_MC:x915", "eba_dim:TYA": "eba_TA:x125", "unit": "$baseCurrency"}, "attributes": "$decimalsMonetary"}, {"code": "dp435529", "dimensions": {"concept": "eba_met:md103", "eba_dim:BAS": "eba_BA:x17", "eba_dim:CCA": "eba_CA:x2", "eba_dim:FRM": "eba_MC:x424", "eba_dim:TIT": "eba_RP:x87", "eba_dim:TRE": "eba_MC:x915", "eba_dim:TYA": "eba_TA:x126", "unit": "$baseCurrency"}, "attributes": "$decimalsMonetary"}, {"code": "dp435530", "dimensions": {"concept": "eba_met:md103", "eba_dim:BAS": "eba_BA:x17", "eba_dim:CCA": "eba_CA:x2", "eba_dim:FRM": "eba_MC:x424", "eba_dim:TIT": "eba_RP:x87", "eba_dim:TRE": "eba_MC:x915", "eba_dim:TYA": "eba_TA:x127", "unit": "$baseCurrency"}, "attributes": "$decimalsMonetary"}, {"code": "dp435531", "dimensions": {"concept": "eba_met:md103", "eba_dim:BAS": "eba_BA:x17", "eba_dim:CCA": "eba_CA:x2", "eba_dim:FRM": "eba_MC:x424", "eba_dim:TIT": "eba_RP:x87", "eba_dim:TRE": "eba_MC:x915", "eba_dim:TYA": "eba_TA:x128", "unit": "$baseCurrency"}, "attributes": "$decimalsMonetary"}, {"code": "dp435532", "dimensions": {"concept": "eba_met:md103", "eba_dim:BAS": "eba_BA:x17", "eba_dim:CCA": "eba_CA:x2", "eba_dim:FRM": "eba_MC:x424", "eba_dim:TIT": "eba_RP:x87", "eba_dim:TRE": "eba_MC:x916", "eba_dim:TYA": "eba_TA:x5", "unit": "$baseCurrency"}, "attributes": "$decimalsMonetary"}, {"code": "dp435533", "dimensions": {"concept": "eba_met:md103", "eba_dim:BAS": "eba_BA:x17", "eba_dim:CCA": "eba_CA:x2", "eba_dim:FRM": "eba_MC:x424", "eba_dim:TIT": "eba_RP:x87", "eba_dim:TRE": "eba_MC:x916", "eba_dim:TYA": "eba_TA:x29", "unit": "$baseCurrency"}, "attributes": "$decimalsMonetary"}, {"code": "dp435534", "dimensions": {"concept": "eba_met:md103", "eba_dim:BAS": "eba_BA:x17", "eba_dim:CCA": "eba_CA:x2", "eba_dim:FRM": "eba_MC:x424", "eba_dim:TIT": "eba_RP:x87", "eba_dim:TRE": "eba_MC:x916", "eba_dim:TYA": "eba_TA:x125", "unit": "$baseCurrency"}, "attributes": "$decimalsMonetary"}, {"code": "dp435535", "dimensions": {"concept": "eba_met:md103", "eba_dim:BAS": "eba_BA:x17", "eba_dim:CCA": "eba_CA:x2", "eba_dim:FRM": "eba_MC:x424", "eba_dim:TIT": "eba_RP:x87", "eba_dim:TRE": "eba_MC:x916", "eba_dim:TYA": "eba_TA:x126", "unit": "$baseCurrency"}, "attributes": "$decimalsMonetary"}, {"code": "dp435536", "dimensions": {"concept": "eba_met:md103", "eba_dim:BAS": "eba_BA:x17", "eba_dim:CCA": "eba_CA:x2", "eba_dim:FRM": "eba_MC:x424", "eba_dim:TIT": "eba_RP:x87", "eba_dim:TRE": "eba_MC:x916", "eba_dim:TYA": "eba_TA:x127", "unit": "$baseCurrency"}, "attributes": "$decimalsMonetary"}, {"code": "dp435537", "dimensions": {"concept": "eba_met:md103", "eba_dim:BAS": "eba_BA:x17", "eba_dim:CCA": "eba_CA:x2", "eba_dim:FRM": "eba_MC:x424", "eba_dim:TIT": "eba_RP:x87", "eba_dim:TRE": "eba_MC:x916", "eba_dim:TYA": "eba_TA:x128", "unit": "$baseCurrency"}, "attributes": "$decimalsMonetary"}, {"code": "dp435538", "dimensions": {"concept": "eba_met:md103", "eba_dim:BAS": "eba_BA:x17", "eba_dim:CCA": "eba_CA:x2", "eba_dim:FRM": "eba_MC:x424", "eba_dim:TIT": "eba_RP:x64", "eba_dim:TRE": "eba_MC:x915", "unit": "$baseCurrency"}, "attributes": "$decimalsMonetary"}, {"code": "dp435539", "dimensions": {"concept": "eba_met:md103", "eba_dim:BAS": "eba_BA:x17", "eba_dim:CCA": "eba_CA:x2", "eba_dim:FRM": "eba_MC:x424", "eba_dim:TIT": "eba_RP:x64", "eba_dim:TRE": "eba_MC:x916", "unit": "$baseCurrency"}, "attributes": "$decimalsMonetary"}, {"code": "dp435540", "dimensions": {"concept": "eba_met:md103", "eba_dim:BAS": "eba_BA:x17", "eba_dim:CCA": "eba_CA:x2", "eba_dim:FRM": "eba_MC:x424", "eba_dim:TIT": "eba_RP:x65", "eba_dim:TRE": "eba_MC:x915", "unit": "$baseCurrency"}, "attributes": "$decimalsMonetary"}, {"code": "dp435541", "dimensions": {"concept": "eba_met:md103", "eba_dim:BAS": "eba_BA:x17", "eba_dim:CCA": "eba_CA:x2", "eba_dim:FRM": "eba_MC:x424", "eba_dim:TIT": "eba_RP:x65", "eba_dim:TRE": "eba_MC:x916", "unit": "$baseCurrency"}, "attributes": "$decimalsMonetary"}, {"code": "dp435566", "dimensions": {"concept": "eba_met:md103", "eba_dim:BAS": "eba_BA:x17", "eba_dim:CCA": "eba_CA:x2", "eba_dim:MCV": "eba_MC:x428", "eba_dim:TIT": "eba_RP:x87", "eba_dim:TRE": "eba_MC:x916", "eba_dim:TYA": "eba_TA:x5", "unit": "$baseCurrency"}, "attributes": "$decimalsMonetary"}, {"code": "dp435567", "dimensions": {"concept": "eba_met:md103", "eba_dim:BAS": "eba_BA:x17", "eba_dim:CCA": "eba_CA:x2", "eba_dim:MCV": "eba_MC:x428", "eba_dim:TIT": "eba_RP:x87", "eba_dim:TRE": "eba_MC:x916", "eba_dim:TYA": "eba_TA:x29", "unit": "$baseCurrency"}, "attributes": "$decimalsMonetary"}, {"code": "dp435568", "dimensions": {"concept": "eba_met:md103", "eba_dim:BAS": "eba_BA:x17", "eba_dim:CCA": "eba_CA:x2", "eba_dim:MCV": "eba_MC:x428", "eba_dim:TIT": "eba_RP:x87", "eba_dim:TRE": "eba_MC:x916", "eba_dim:TYA": "eba_TA:x125", "unit": "$baseCurrency"}, "attributes": "$decimalsMonetary"}, {"code": "dp435569", "dimensions": {"concept": "eba_met:md103", "eba_dim:BAS": "eba_BA:x17", "eba_dim:CCA": "eba_CA:x2", "eba_dim:MCV": "eba_MC:x428", "eba_dim:TIT": "eba_RP:x87", "eba_dim:TRE": "eba_MC:x916", "eba_dim:TYA": "eba_TA:x126", "unit": "$baseCurrency"}, "attributes": "$decimalsMonetary"}, {"code": "dp435570", "dimensions": {"concept": "eba_met:md103", "eba_dim:BAS": "eba_BA:x17", "eba_dim:CCA": "eba_CA:x2", "eba_dim:MCV": "eba_MC:x428", "eba_dim:TIT": "eba_RP:x87", "eba_dim:TRE": "eba_MC:x916", "eba_dim:TYA": "eba_TA:x127", "unit": "$baseCurrency"}, "attributes": "$decimalsMonetary"}, {"code": "dp435571", "dimensions": {"concept": "eba_met:md103", "eba_dim:BAS": "eba_BA:x17", "eba_dim:CCA": "eba_CA:x2", "eba_dim:MCV": "eba_MC:x428", "eba_dim:TIT": "eba_RP:x87", "eba_dim:TRE": "eba_MC:x916", "eba_dim:TYA": "eba_TA:x128", "unit": "$baseCurrency"}, "attributes": "$decimalsMonetary"}, {"code": "dp435572", "dimensions": {"concept": "eba_met:md103", "eba_dim:BAS": "eba_BA:x17", "eba_dim:CCA": "eba_CA:x2", "eba_dim:MCV": "eba_MC:x428", "eba_dim:TIT": "eba_RP:x64", "eba_dim:TRE": "eba_MC:x916", "unit": "$baseCurrency"}, "attributes": "$decimalsMonetary"}, {"code": "dp435573", "dimensions": {"concept": "eba_met:md103", "eba_dim:BAS": "eba_BA:x17", "eba_dim:CCA": "eba_CA:x2", "eba_dim:MCV": "eba_MC:x428", "eba_dim:TIT": "eba_RP:x65", "eba_dim:TRE": "eba_MC:x916", "unit": "$baseCurrency"}, "attributes": "$decimalsMonetary"}, {"code": "dp435574", "dimensions": {"concept": "eba_met:md103", "eba_dim:BAS": "eba_BA:x17", "eba_dim:CCA": "eba_CA:x2", "eba_dim:MCV": "eba_MC:x438", "eba_dim:TIT": "eba_RP:x87", "eba_dim:TRE": "eba_MC:x916", "eba_dim:TYA": "eba_TA:x5", "unit": "$baseCurrency"}, "attributes": "$decimalsMonetary"}, {"code": "dp435575", "dimensions": {"concept": "eba_met:md103", "eba_dim:BAS": "eba_BA:x17", "eba_dim:CCA": "eba_CA:x2", "eba_dim:MCV": "eba_MC:x438", "eba_dim:TIT": "eba_RP:x87", "eba_dim:TRE": "eba_MC:x916", "eba_dim:TYA": "eba_TA:x29", "unit": "$baseCurrency"}, "attributes": "$decimalsMonetary"}, {"code": "dp435576", "dimensions": {"concept": "eba_met:md103", "eba_dim:BAS": "eba_BA:x17", "eba_dim:CCA": "eba_CA:x2", "eba_dim:MCV": "eba_MC:x438", "eba_dim:TIT": "eba_RP:x87", "eba_dim:TRE": "eba_MC:x916", "eba_dim:TYA": "eba_TA:x125", "unit": "$baseCurrency"}, "attributes": "$decimalsMonetary"}, {"code": "dp435577", "dimensions": {"concept": "eba_met:md103", "eba_dim:BAS": "eba_BA:x17", "eba_dim:CCA": "eba_CA:x2", "eba_dim:MCV": "eba_MC:x438", "eba_dim:TIT": "eba_RP:x87", "eba_dim:TRE": "eba_MC:x916", "eba_dim:TYA": "eba_TA:x126", "unit": "$baseCurrency"}, "attributes": "$decimalsMonetary"}, {"code": "dp435578", "dimensions": {"concept": "eba_met:md103", "eba_dim:BAS": "eba_BA:x17", "eba_dim:CCA": "eba_CA:x2", "eba_dim:MCV": "eba_MC:x438", "eba_dim:TIT": "eba_RP:x87", "eba_dim:TRE": "eba_MC:x916", "eba_dim:TYA": "eba_TA:x127", "unit": "$baseCurrency"}, "attributes": "$decimalsMonetary"}, {"code": "dp435579", "dimensions": {"concept": "eba_met:md103", "eba_dim:BAS": "eba_BA:x17", "eba_dim:CCA": "eba_CA:x2", "eba_dim:MCV": "eba_MC:x438", "eba_dim:TIT": "eba_RP:x87", "eba_dim:TRE": "eba_MC:x916", "eba_dim:TYA": "eba_TA:x128", "unit": "$baseCurrency"}, "attributes": "$decimalsMonetary"}, {"code": "dp435580", "dimensions": {"concept": "eba_met:md103", "eba_dim:BAS": "eba_BA:x17", "eba_dim:CCA": "eba_CA:x2", "eba_dim:MCV": "eba_MC:x438", "eba_dim:TIT": "eba_RP:x64", "eba_dim:TRE": "eba_MC:x916", "unit": "$baseCurrency"}, "attributes": "$decimalsMonetary"}, {"code": "dp435581", "dimensions": {"concept": "eba_met:md103", "eba_dim:BAS": "eba_BA:x17", "eba_dim:CCA": "eba_CA:x2", "eba_dim:MCV": "eba_MC:x438", "eba_dim:TIT": "eba_RP:x65", "eba_dim:TRE": "eba_MC:x916", "unit": "$baseCurrency"}, "attributes": "$decimalsMonetary"}, {"code": "dp435582", "dimensions": {"concept": "eba_met:md103", "eba_dim:BAS": "eba_BA:x17", "eba_dim:CCA": "eba_CA:x2", "eba_dim:TIT": "eba_RP:x87", "eba_dim:TRE": "eba_MC:x915", "eba_dim:TYA": "eba_TA:x5", "unit": "$baseCurrency"}, "attributes": "$decimalsMonetary"}, {"code": "dp435583", "dimensions": {"concept": "eba_met:md103", "eba_dim:BAS": "eba_BA:x17", "eba_dim:CCA": "eba_CA:x2", "eba_dim:TIT": "eba_RP:x87", "eba_dim:TRE": "eba_MC:x915", "eba_dim:TYA": "eba_TA:x29", "unit": "$baseCurrency"}, "attributes": "$decimalsMonetary"}, {"code": "dp435584", "dimensions": {"concept": "eba_met:md103", "eba_dim:BAS": "eba_BA:x17", "eba_dim:CCA": "eba_CA:x2", "eba_dim:TIT": "eba_RP:x87", "eba_dim:TRE": "eba_MC:x915", "eba_dim:TYA": "eba_TA:x125", "unit": "$baseCurrency"}, "attributes": "$decimalsMonetary"}, {"code": "dp435585", "dimensions": {"concept": "eba_met:md103", "eba_dim:BAS": "eba_BA:x17", "eba_dim:CCA": "eba_CA:x2", "eba_dim:TIT": "eba_RP:x87", "eba_dim:TRE": "eba_MC:x915", "eba_dim:TYA": "eba_TA:x126", "unit": "$baseCurrency"}, "attributes": "$decimalsMonetary"}, {"code": "dp435586", "dimensions": {"concept": "eba_met:md103", "eba_dim:BAS": "eba_BA:x17", "eba_dim:CCA": "eba_CA:x2", "eba_dim:TIT": "eba_RP:x87", "eba_dim:TRE": "eba_MC:x915", "eba_dim:TYA": "eba_TA:x127", "unit": "$baseCurrency"}, "attributes": "$decimalsMonetary"}, {"code": "dp435587", "dimensions": {"concept": "eba_met:md103", "eba_dim:BAS": "eba_BA:x17", "eba_dim:CCA": "eba_CA:x2", "eba_dim:TIT": "eba_RP:x87", "eba_dim:TRE": "eba_MC:x915", "eba_dim:TYA": "eba_TA:x128", "unit": "$baseCurrency"}, "attributes": "$decimalsMonetary"}, {"code": "dp435588", "dimensions": {"concept": "eba_met:md103", "eba_dim:BAS": "eba_BA:x17", "eba_dim:CCA": "eba_CA:x2", "eba_dim:TIT": "eba_RP:x87", "eba_dim:TRE": "eba_MC:x916", "eba_dim:TYA": "eba_TA:x5", "unit": "$baseCurrency"}, "attributes": "$decimalsMonetary"}, {"code": "dp435589", "dimensions": {"concept": "eba_met:md103", "eba_dim:BAS": "eba_BA:x17", "eba_dim:CCA": "eba_CA:x2", "eba_dim:TIT": "eba_RP:x87", "eba_dim:TRE": "eba_MC:x916", "eba_dim:TYA": "eba_TA:x29", "unit": "$baseCurrency"}, "attributes": "$decimalsMonetary"}, {"code": "dp435590", "dimensions": {"concept": "eba_met:md103", "eba_dim:BAS": "eba_BA:x17", "eba_dim:CCA": "eba_CA:x2", "eba_dim:TIT": "eba_RP:x87", "eba_dim:TRE": "eba_MC:x916", "eba_dim:TYA": "eba_TA:x125", "unit": "$baseCurrency"}, "attributes": "$decimalsMonetary"}, {"code": "dp435591", "dimensions": {"concept": "eba_met:md103", "eba_dim:BAS": "eba_BA:x17", "eba_dim:CCA": "eba_CA:x2", "eba_dim:TIT": "eba_RP:x87", "eba_dim:TRE": "eba_MC:x916", "eba_dim:TYA": "eba_TA:x126", "unit": "$baseCurrency"}, "attributes": "$decimalsMonetary"}, {"code": "dp435592", "dimensions": {"concept": "eba_met:md103", "eba_dim:BAS": "eba_BA:x17", "eba_dim:CCA": "eba_CA:x2", "eba_dim:TIT": "eba_RP:x87", "eba_dim:TRE": "eba_MC:x916", "eba_dim:TYA": "eba_TA:x127", "unit": "$baseCurrency"}, "attributes": "$decimalsMonetary"}, {"code": "dp435593", "dimensions": {"concept": "eba_met:md103", "eba_dim:BAS": "eba_BA:x17", "eba_dim:CCA": "eba_CA:x2", "eba_dim:TIT": "eba_RP:x87", "eba_dim:TRE": "eba_MC:x916", "eba_dim:TYA": "eba_TA:x128", "unit": "$baseCurrency"}, "attributes": "$decimalsMonetary"}, {"code": "dp435594", "dimensions": {"concept": "eba_met:md103", "eba_dim:BAS": "eba_BA:x17", "eba_dim:CCA": "eba_CA:x2", "eba_dim:TIT": "eba_RP:x64", "eba_dim:TRE": "eba_MC:x915", "unit": "$baseCurrency"}, "attributes": "$decimalsMonetary"}, {"code": "dp435597", "dimensions": {"concept": "eba_met:md103", "eba_dim:BAS": "eba_BA:x17", "eba_dim:CCA": "eba_CA:x2", "eba_dim:TIT": "eba_RP:x65", "eba_dim:TRE": "eba_MC:x915", "unit": "$baseCurrency"}, "attributes": "$decimalsMonetary"}, {"code": "dp436824", "dimensions": {"concept": "eba_met:ii699", "eba_dim:BAS": "eba_BA:x3", "eba_dim:MCV": "eba_MC:x912", "eba_dim:MCY": "eba_MC:x22", "eba_dim:TIT": "eba_RP:x87", "eba_dim:TYA": "eba_TA:x5"}, "attributes": "$decimalsInteger"}, {"code": "dp436825", "dimensions": {"concept": "eba_met:ii699", "eba_dim:BAS": "eba_BA:x3", "eba_dim:MCV": "eba_MC:x912", "eba_dim:MCY": "eba_MC:x22", "eba_dim:TIT": "eba_RP:x87", "eba_dim:TYA": "eba_TA:x29"}, "attributes": "$decimalsInteger"}, {"code": "dp436826", "dimensions": {"concept": "eba_met:ii699", "eba_dim:BAS": "eba_BA:x3", "eba_dim:MCV": "eba_MC:x912", "eba_dim:MCY": "eba_MC:x22", "eba_dim:TIT": "eba_RP:x87", "eba_dim:TYA": "eba_TA:x125"}, "attributes": "$decimalsInteger"}, {"code": "dp436827", "dimensions": {"concept": "eba_met:ii699", "eba_dim:BAS": "eba_BA:x3", "eba_dim:MCV": "eba_MC:x912", "eba_dim:MCY": "eba_MC:x22", "eba_dim:TIT": "eba_RP:x87", "eba_dim:TYA": "eba_TA:x126"}, "attributes": "$decimalsInteger"}, {"code": "dp436828", "dimensions": {"concept": "eba_met:ii699", "eba_dim:BAS": "eba_BA:x3", "eba_dim:MCV": "eba_MC:x912", "eba_dim:MCY": "eba_MC:x22", "eba_dim:TIT": "eba_RP:x87", "eba_dim:TYA": "eba_TA:x127"}, "attributes": "$decimalsInteger"}, {"code": "dp436829", "dimensions": {"concept": "eba_met:ii699", "eba_dim:BAS": "eba_BA:x3", "eba_dim:MCV": "eba_MC:x912", "eba_dim:MCY": "eba_MC:x22", "eba_dim:TIT": "eba_RP:x87", "eba_dim:TYA": "eba_TA:x128"}, "attributes": "$decimalsInteger"}, {"code": "dp436830", "dimensions": {"concept": "eba_met:ii699", "eba_dim:BAS": "eba_BA:x3", "eba_dim:MCV": "eba_MC:x912", "eba_dim:MCY": "eba_MC:x22", "eba_dim:TIT": "eba_RP:x64"}, "attributes": "$decimalsInteger"}, {"code": "dp436831", "dimensions": {"concept": "eba_met:ii699", "eba_dim:BAS": "eba_BA:x3", "eba_dim:MCV": "eba_MC:x912", "eba_dim:MCY": "eba_MC:x22", "eba_dim:TIT": "eba_RP:x65"}, "attributes": "$decimalsInteger"}, {"code": "dp436832", "dimensions": {"concept": "eba_met:ii699", "eba_dim:BAS": "eba_BA:x3", "eba_dim:MCV": "eba_MC:x428", "eba_dim:MCY": "eba_MC:x22", "eba_dim:TIT": "eba_RP:x87", "eba_dim:TRE": "eba_MC:x916", "eba_dim:TYA": "eba_TA:x5"}, "attributes": "$decimalsInteger"}, {"code": "dp436833", "dimensions": {"concept": "eba_met:ii699", "eba_dim:BAS": "eba_BA:x3", "eba_dim:MCV": "eba_MC:x428", "eba_dim:MCY": "eba_MC:x22", "eba_dim:TIT": "eba_RP:x87", "eba_dim:TRE": "eba_MC:x916", "eba_dim:TYA": "eba_TA:x29"}, "attributes": "$decimalsInteger"}, {"code": "dp436834", "dimensions": {"concept": "eba_met:ii699", "eba_dim:BAS": "eba_BA:x3", "eba_dim:MCV": "eba_MC:x428", "eba_dim:MCY": "eba_MC:x22", "eba_dim:TIT": "eba_RP:x87", "eba_dim:TRE": "eba_MC:x916", "eba_dim:TYA": "eba_TA:x125"}, "attributes": "$decimalsInteger"}, {"code": "dp436835", "dimensions": {"concept": "eba_met:ii699", "eba_dim:BAS": "eba_BA:x3", "eba_dim:MCV": "eba_MC:x428", "eba_dim:MCY": "eba_MC:x22", "eba_dim:TIT": "eba_RP:x87", "eba_dim:TRE": "eba_MC:x916", "eba_dim:TYA": "eba_TA:x126"}, "attributes": "$decimalsInteger"}, {"code": "dp436836", "dimensions": {"concept": "eba_met:ii699", "eba_dim:BAS": "eba_BA:x3", "eba_dim:MCV": "eba_MC:x428", "eba_dim:MCY": "eba_MC:x22", "eba_dim:TIT": "eba_RP:x87", "eba_dim:TRE": "eba_MC:x916", "eba_dim:TYA": "eba_TA:x127"}, "attributes": "$decimalsInteger"}, {"code": "dp436837", "dimensions": {"concept": "eba_met:ii699", "eba_dim:BAS": "eba_BA:x3", "eba_dim:MCV": "eba_MC:x428", "eba_dim:MCY": "eba_MC:x22", "eba_dim:TIT": "eba_RP:x87", "eba_dim:TRE": "eba_MC:x916", "eba_dim:TYA": "eba_TA:x128"}, "attributes": "$decimalsInteger"}, {"code": "dp436838", "dimensions": {"concept": "eba_met:ii699", "eba_dim:BAS": "eba_BA:x3", "eba_dim:MCV": "eba_MC:x428", "eba_dim:MCY": "eba_MC:x22", "eba_dim:TIT": "eba_RP:x64", "eba_dim:TRE": "eba_MC:x916"}, "attributes": "$decimalsInteger"}, {"code": "dp436839", "dimensions": {"concept": "eba_met:ii699", "eba_dim:BAS": "eba_BA:x3", "eba_dim:MCV": "eba_MC:x428", "eba_dim:MCY": "eba_MC:x22", "eba_dim:TIT": "eba_RP:x65", "eba_dim:TRE": "eba_MC:x916"}, "attributes": "$decimalsInteger"}, {"code": "dp436848", "dimensions": {"concept": "eba_met:ii699", "eba_dim:BAS": "eba_BA:x17", "eba_dim:TIT": "eba_RP:x87", "eba_dim:TRE": "eba_MC:x435", "eba_dim:TYA": "eba_TA:x5"}, "attributes": "$decimalsInteger"}, {"code": "dp436849", "dimensions": {"concept": "eba_met:ii699", "eba_dim:BAS": "eba_BA:x17", "eba_dim:TIT": "eba_RP:x87", "eba_dim:TRE": "eba_MC:x435", "eba_dim:TYA": "eba_TA:x29"}, "attributes": "$decimalsInteger"}, {"code": "dp436850", "dimensions": {"concept": "eba_met:ii699", "eba_dim:BAS": "eba_BA:x17", "eba_dim:TIT": "eba_RP:x87", "eba_dim:TRE": "eba_MC:x435", "eba_dim:TYA": "eba_TA:x125"}, "attributes": "$decimalsInteger"}, {"code": "dp436851", "dimensions": {"concept": "eba_met:ii699", "eba_dim:BAS": "eba_BA:x17", "eba_dim:TIT": "eba_RP:x87", "eba_dim:TRE": "eba_MC:x435", "eba_dim:TYA": "eba_TA:x126"}, "attributes": "$decimalsInteger"}, {"code": "dp436852", "dimensions": {"concept": "eba_met:ii699", "eba_dim:BAS": "eba_BA:x17", "eba_dim:TIT": "eba_RP:x87", "eba_dim:TRE": "eba_MC:x435", "eba_dim:TYA": "eba_TA:x127"}, "attributes": "$decimalsInteger"}, {"code": "dp436853", "dimensions": {"concept": "eba_met:ii699", "eba_dim:BAS": "eba_BA:x17", "eba_dim:TIT": "eba_RP:x87", "eba_dim:TRE": "eba_MC:x435", "eba_dim:TYA": "eba_TA:x128"}, "attributes": "$decimalsInteger"}, {"code": "dp436854", "dimensions": {"concept": "eba_met:ii699", "eba_dim:BAS": "eba_BA:x17", "eba_dim:TIT": "eba_RP:x64", "eba_dim:TRE": "eba_MC:x435"}, "attributes": "$decimalsInteger"}, {"code": "dp436855", "dimensions": {"concept": "eba_met:ii699", "eba_dim:BAS": "eba_BA:x17", "eba_dim:TIT": "eba_RP:x65", "eba_dim:TRE": "eba_MC:x435"}, "attributes": "$decimalsInteger"}, {"code": "dp438087", "dimensions": {"concept": "eba_met:ri882", "eba_dim:BAS": "eba_BA:x17", "eba_dim:TIT": "eba_RP:x87", "eba_dim:TYA": "eba_TA:x5"}, "attributes": "$decimalsDecimal"}, {"code": "dp438088", "dimensions": {"concept": "eba_met:ri882", "eba_dim:BAS": "eba_BA:x17", "eba_dim:TIT": "eba_RP:x87", "eba_dim:TYA": "eba_TA:x29"}, "attributes": "$decimalsDecimal"}, {"code": "dp438089", "dimensions": {"concept": "eba_met:ri882", "eba_dim:BAS": "eba_BA:x17", "eba_dim:TIT": "eba_RP:x87", "eba_dim:TYA": "eba_TA:x125"}, "attributes": "$decimalsDecimal"}, {"code": "dp438090", "dimensions": {"concept": "eba_met:ri882", "eba_dim:BAS": "eba_BA:x17", "eba_dim:TIT": "eba_RP:x87", "eba_dim:TYA": "eba_TA:x126"}, "attributes": "$decimalsDecimal"}, {"code": "dp438091", "dimensions": {"concept": "eba_met:ri882", "eba_dim:BAS": "eba_BA:x17", "eba_dim:TIT": "eba_RP:x87", "eba_dim:TYA": "eba_TA:x127"}, "attributes": "$decimalsDecimal"}, {"code": "dp438092", "dimensions": {"concept": "eba_met:ri882", "eba_dim:BAS": "eba_BA:x17", "eba_dim:TIT": "eba_RP:x87", "eba_dim:TYA": "eba_TA:x128"}, "attributes": "$decimalsDecimal"}, {"code": "dp438107", "dimensions": {"concept": "eba_met:mi776", "eba_dim:BAS": "eba_BA:x17", "eba_dim:CCA": "eba_CA:x2", "eba_dim:FRM": "eba_MC:x412", "eba_dim:TIT": "eba_RP:x87", "eba_dim:TRE": "eba_MC:x916", "eba_dim:TYA": "eba_TA:x5", "unit": "$baseCurrency"}, "attributes": "$decimalsMonetary"}, {"code": "dp438108", "dimensions": {"concept": "eba_met:mi776", "eba_dim:BAS": "eba_BA:x17", "eba_dim:CCA": "eba_CA:x2", "eba_dim:FRM": "eba_MC:x412", "eba_dim:TIT": "eba_RP:x87", "eba_dim:TRE": "eba_MC:x916", "eba_dim:TYA": "eba_TA:x29", "unit": "$baseCurrency"}, "attributes": "$decimalsMonetary"}, {"code": "dp438109", "dimensions": {"concept": "eba_met:mi776", "eba_dim:BAS": "eba_BA:x17", "eba_dim:CCA": "eba_CA:x2", "eba_dim:FRM": "eba_MC:x412", "eba_dim:TIT": "eba_RP:x87", "eba_dim:TRE": "eba_MC:x916", "eba_dim:TYA": "eba_TA:x125", "unit": "$baseCurrency"}, "attributes": "$decimalsMonetary"}, {"code": "dp438110", "dimensions": {"concept": "eba_met:mi776", "eba_dim:BAS": "eba_BA:x17", "eba_dim:CCA": "eba_CA:x2", "eba_dim:FRM": "eba_MC:x412", "eba_dim:TIT": "eba_RP:x87", "eba_dim:TRE": "eba_MC:x916", "eba_dim:TYA": "eba_TA:x126", "unit": "$baseCurrency"}, "attributes": "$decimalsMonetary"}, {"code": "dp438111", "dimensions": {"concept": "eba_met:mi776", "eba_dim:BAS": "eba_BA:x17", "eba_dim:CCA": "eba_CA:x2", "eba_dim:FRM": "eba_MC:x412", "eba_dim:TIT": "eba_RP:x87", "eba_dim:TRE": "eba_MC:x916", "eba_dim:TYA": "eba_TA:x127", "unit": "$baseCurrency"}, "attributes": "$decimalsMonetary"}, {"code": "dp438112", "dimensions": {"concept": "eba_met:mi776", "eba_dim:BAS": "eba_BA:x17", "eba_dim:CCA": "eba_CA:x2", "eba_dim:FRM": "eba_MC:x412", "eba_dim:TIT": "eba_RP:x87", "eba_dim:TRE": "eba_MC:x916", "eba_dim:TYA": "eba_TA:x128", "unit": "$baseCurrency"}, "attributes": "$decimalsMonetary"}, {"code": "dp438113", "dimensions": {"concept": "eba_met:mi776", "eba_dim:BAS": "eba_BA:x17", "eba_dim:CCA": "eba_CA:x2", "eba_dim:FRM": "eba_MC:x412", "eba_dim:TIT": "eba_RP:x64", "eba_dim:TRE": "eba_MC:x916", "unit": "$baseCurrency"}, "attributes": "$decimalsMonetary"}, {"code": "dp438114", "dimensions": {"concept": "eba_met:mi776", "eba_dim:BAS": "eba_BA:x17", "eba_dim:CCA": "eba_CA:x2", "eba_dim:FRM": "eba_MC:x412", "eba_dim:TIT": "eba_RP:x65", "eba_dim:TRE": "eba_MC:x916", "unit": "$baseCurrency"}, "attributes": "$decimalsMonetary"}, {"code": "dp438123", "dimensions": {"concept": "eba_met:mi776", "eba_dim:BAS": "eba_BA:x17", "eba_dim:CCA": "eba_CA:x2", "eba_dim:FRM": "eba_MC:x417", "eba_dim:TIT": "eba_RP:x87", "eba_dim:TRE": "eba_MC:x916", "eba_dim:TYA": "eba_TA:x5", "unit": "$baseCurrency"}, "attributes": "$decimalsMonetary"}, {"code": "dp438124", "dimensions": {"concept": "eba_met:mi776", "eba_dim:BAS": "eba_BA:x17", "eba_dim:CCA": "eba_CA:x2", "eba_dim:FRM": "eba_MC:x417", "eba_dim:TIT": "eba_RP:x87", "eba_dim:TRE": "eba_MC:x916", "eba_dim:TYA": "eba_TA:x29", "unit": "$baseCurrency"}, "attributes": "$decimalsMonetary"}, {"code": "dp438125", "dimensions": {"concept": "eba_met:mi776", "eba_dim:BAS": "eba_BA:x17", "eba_dim:CCA": "eba_CA:x2", "eba_dim:FRM": "eba_MC:x417", "eba_dim:TIT": "eba_RP:x87", "eba_dim:TRE": "eba_MC:x916", "eba_dim:TYA": "eba_TA:x125", "unit": "$baseCurrency"}, "attributes": "$decimalsMonetary"}, {"code": "dp438126", "dimensions": {"concept": "eba_met:mi776", "eba_dim:BAS": "eba_BA:x17", "eba_dim:CCA": "eba_CA:x2", "eba_dim:FRM": "eba_MC:x417", "eba_dim:TIT": "eba_RP:x87", "eba_dim:TRE": "eba_MC:x916", "eba_dim:TYA": "eba_TA:x126", "unit": "$baseCurrency"}, "attributes": "$decimalsMonetary"}, {"code": "dp438127", "dimensions": {"concept": "eba_met:mi776", "eba_dim:BAS": "eba_BA:x17", "eba_dim:CCA": "eba_CA:x2", "eba_dim:FRM": "eba_MC:x417", "eba_dim:TIT": "eba_RP:x87", "eba_dim:TRE": "eba_MC:x916", "eba_dim:TYA": "eba_TA:x127", "unit": "$baseCurrency"}, "attributes": "$decimalsMonetary"}, {"code": "dp438128", "dimensions": {"concept": "eba_met:mi776", "eba_dim:BAS": "eba_BA:x17", "eba_dim:CCA": "eba_CA:x2", "eba_dim:FRM": "eba_MC:x417", "eba_dim:TIT": "eba_RP:x87", "eba_dim:TRE": "eba_MC:x916", "eba_dim:TYA": "eba_TA:x128", "unit": "$baseCurrency"}, "attributes": "$decimalsMonetary"}, {"code": "dp438129", "dimensions": {"concept": "eba_met:mi776", "eba_dim:BAS": "eba_BA:x17", "eba_dim:CCA": "eba_CA:x2", "eba_dim:FRM": "eba_MC:x417", "eba_dim:TIT": "eba_RP:x64", "eba_dim:TRE": "eba_MC:x916", "unit": "$baseCurrency"}, "attributes": "$decimalsMonetary"}, {"code": "dp438130", "dimensions": {"concept": "eba_met:mi776", "eba_dim:BAS": "eba_BA:x17", "eba_dim:CCA": "eba_CA:x2", "eba_dim:FRM": "eba_MC:x417", "eba_dim:TIT": "eba_RP:x65", "eba_dim:TRE": "eba_MC:x916", "unit": "$baseCurrency"}, "attributes": "$decimalsMonetary"}, {"code": "dp438139", "dimensions": {"concept": "eba_met:mi776", "eba_dim:BAS": "eba_BA:x17", "eba_dim:CCA": "eba_CA:x2", "eba_dim:FRM": "eba_MC:x424", "eba_dim:TIT": "eba_RP:x87", "eba_dim:TRE": "eba_MC:x916", "eba_dim:TYA": "eba_TA:x5", "unit": "$baseCurrency"}, "attributes": "$decimalsMonetary"}, {"code": "dp438140", "dimensions": {"concept": "eba_met:mi776", "eba_dim:BAS": "eba_BA:x17", "eba_dim:CCA": "eba_CA:x2", "eba_dim:FRM": "eba_MC:x424", "eba_dim:TIT": "eba_RP:x87", "eba_dim:TRE": "eba_MC:x916", "eba_dim:TYA": "eba_TA:x29", "unit": "$baseCurrency"}, "attributes": "$decimalsMonetary"}, {"code": "dp438141", "dimensions": {"concept": "eba_met:mi776", "eba_dim:BAS": "eba_BA:x17", "eba_dim:CCA": "eba_CA:x2", "eba_dim:FRM": "eba_MC:x424", "eba_dim:TIT": "eba_RP:x87", "eba_dim:TRE": "eba_MC:x916", "eba_dim:TYA": "eba_TA:x125", "unit": "$baseCurrency"}, "attributes": "$decimalsMonetary"}, {"code": "dp438142", "dimensions": {"concept": "eba_met:mi776", "eba_dim:BAS": "eba_BA:x17", "eba_dim:CCA": "eba_CA:x2", "eba_dim:FRM": "eba_MC:x424", "eba_dim:TIT": "eba_RP:x87", "eba_dim:TRE": "eba_MC:x916", "eba_dim:TYA": "eba_TA:x126", "unit": "$baseCurrency"}, "attributes": "$decimalsMonetary"}, {"code": "dp438143", "dimensions": {"concept": "eba_met:mi776", "eba_dim:BAS": "eba_BA:x17", "eba_dim:CCA": "eba_CA:x2", "eba_dim:FRM": "eba_MC:x424", "eba_dim:TIT": "eba_RP:x87", "eba_dim:TRE": "eba_MC:x916", "eba_dim:TYA": "eba_TA:x127", "unit": "$baseCurrency"}, "attributes": "$decimalsMonetary"}, {"code": "dp438144", "dimensions": {"concept": "eba_met:mi776", "eba_dim:BAS": "eba_BA:x17", "eba_dim:CCA": "eba_CA:x2", "eba_dim:FRM": "eba_MC:x424", "eba_dim:TIT": "eba_RP:x87", "eba_dim:TRE": "eba_MC:x916", "eba_dim:TYA": "eba_TA:x128", "unit": "$baseCurrency"}, "attributes": "$decimalsMonetary"}, {"code": "dp438145", "dimensions": {"concept": "eba_met:mi776", "eba_dim:BAS": "eba_BA:x17", "eba_dim:CCA": "eba_CA:x2", "eba_dim:FRM": "eba_MC:x424", "eba_dim:TIT": "eba_RP:x64", "eba_dim:TRE": "eba_MC:x916", "unit": "$baseCurrency"}, "attributes": "$decimalsMonetary"}, {"code": "dp438146", "dimensions": {"concept": "eba_met:mi776", "eba_dim:BAS": "eba_BA:x17", "eba_dim:CCA": "eba_CA:x2", "eba_dim:FRM": "eba_MC:x424", "eba_dim:TIT": "eba_RP:x65", "eba_dim:TRE": "eba_MC:x916", "unit": "$baseCurrency"}, "attributes": "$decimalsMonetary"}, {"code": "dp438155", "dimensions": {"concept": "eba_met:mi776", "eba_dim:BAS": "eba_BA:x17", "eba_dim:CCA": "eba_CA:x2", "eba_dim:TIT": "eba_RP:x87", "eba_dim:TRE": "eba_MC:x916", "eba_dim:TWR": "eba_RF:x53", "eba_dim:TYA": "eba_TA:x5", "unit": "$baseCurrency"}, "attributes": "$decimalsMonetary"}, {"code": "dp438156", "dimensions": {"concept": "eba_met:mi776", "eba_dim:BAS": "eba_BA:x17", "eba_dim:CCA": "eba_CA:x2", "eba_dim:TIT": "eba_RP:x87", "eba_dim:TRE": "eba_MC:x916", "eba_dim:TWR": "eba_RF:x53", "eba_dim:TYA": "eba_TA:x29", "unit": "$baseCurrency"}, "attributes": "$decimalsMonetary"}, {"code": "dp438157", "dimensions": {"concept": "eba_met:mi776", "eba_dim:BAS": "eba_BA:x17", "eba_dim:CCA": "eba_CA:x2", "eba_dim:TIT": "eba_RP:x87", "eba_dim:TRE": "eba_MC:x916", "eba_dim:TWR": "eba_RF:x53", "eba_dim:TYA": "eba_TA:x125", "unit": "$baseCurrency"}, "attributes": "$decimalsMonetary"}, {"code": "dp438158", "dimensions": {"concept": "eba_met:mi776", "eba_dim:BAS": "eba_BA:x17", "eba_dim:CCA": "eba_CA:x2", "eba_dim:TIT": "eba_RP:x87", "eba_dim:TRE": "eba_MC:x916", "eba_dim:TWR": "eba_RF:x53", "eba_dim:TYA": "eba_TA:x126", "unit": "$baseCurrency"}, "attributes": "$decimalsMonetary"}, {"code": "dp438159", "dimensions": {"concept": "eba_met:mi776", "eba_dim:BAS": "eba_BA:x17", "eba_dim:CCA": "eba_CA:x2", "eba_dim:TIT": "eba_RP:x87", "eba_dim:TRE": "eba_MC:x916", "eba_dim:TWR": "eba_RF:x53", "eba_dim:TYA": "eba_TA:x127", "unit": "$baseCurrency"}, "attributes": "$decimalsMonetary"}, {"code": "dp438160", "dimensions": {"concept": "eba_met:mi776", "eba_dim:BAS": "eba_BA:x17", "eba_dim:CCA": "eba_CA:x2", "eba_dim:TIT": "eba_RP:x87", "eba_dim:TRE": "eba_MC:x916", "eba_dim:TWR": "eba_RF:x53", "eba_dim:TYA": "eba_TA:x128", "unit": "$baseCurrency"}, "attributes": "$decimalsMonetary"}, {"code": "dp438161", "dimensions": {"concept": "eba_met:mi776", "eba_dim:BAS": "eba_BA:x17", "eba_dim:CCA": "eba_CA:x2", "eba_dim:TIT": "eba_RP:x87", "eba_dim:TRE": "eba_MC:x916", "eba_dim:TYA": "eba_TA:x5", "unit": "$baseCurrency"}, "attributes": "$decimalsMonetary"}, {"code": "dp438162", "dimensions": {"concept": "eba_met:mi776", "eba_dim:BAS": "eba_BA:x17", "eba_dim:CCA": "eba_CA:x2", "eba_dim:TIT": "eba_RP:x87", "eba_dim:TRE": "eba_MC:x916", "eba_dim:TYA": "eba_TA:x29", "unit": "$baseCurrency"}, "attributes": "$decimalsMonetary"}, {"code": "dp438163", "dimensions": {"concept": "eba_met:mi776", "eba_dim:BAS": "eba_BA:x17", "eba_dim:CCA": "eba_CA:x2", "eba_dim:TIT": "eba_RP:x87", "eba_dim:TRE": "eba_MC:x916", "eba_dim:TYA": "eba_TA:x125", "unit": "$baseCurrency"}, "attributes": "$decimalsMonetary"}, {"code": "dp438164", "dimensions": {"concept": "eba_met:mi776", "eba_dim:BAS": "eba_BA:x17", "eba_dim:CCA": "eba_CA:x2", "eba_dim:TIT": "eba_RP:x87", "eba_dim:TRE": "eba_MC:x916", "eba_dim:TYA": "eba_TA:x126", "unit": "$baseCurrency"}, "attributes": "$decimalsMonetary"}, {"code": "dp438165", "dimensions": {"concept": "eba_met:mi776", "eba_dim:BAS": "eba_BA:x17", "eba_dim:CCA": "eba_CA:x2", "eba_dim:TIT": "eba_RP:x87", "eba_dim:TRE": "eba_MC:x916", "eba_dim:TYA": "eba_TA:x127", "unit": "$baseCurrency"}, "attributes": "$decimalsMonetary"}, {"code": "dp438166", "dimensions": {"concept": "eba_met:mi776", "eba_dim:BAS": "eba_BA:x17", "eba_dim:CCA": "eba_CA:x2", "eba_dim:TIT": "eba_RP:x87", "eba_dim:TRE": "eba_MC:x916", "eba_dim:TYA": "eba_TA:x128", "unit": "$baseCurrency"}, "attributes": "$decimalsMonetary"}, {"code": "dp438167", "dimensions": {"concept": "eba_met:mi776", "eba_dim:BAS": "eba_BA:x17", "eba_dim:CCA": "eba_CA:x2", "eba_dim:TIT": "eba_RP:x64", "eba_dim:TRE": "eba_MC:x916", "unit": "$baseCurrency"}, "attributes": "$decimalsMonetary"}, {"code": "dp438168", "dimensions": {"concept": "eba_met:mi776", "eba_dim:BAS": "eba_BA:x17", "eba_dim:CCA": "eba_CA:x2", "eba_dim:TIT": "eba_RP:x64", "eba_dim:TRE": "eba_MC:x916", "eba_dim:TWR": "eba_RF:x53", "unit": "$baseCurrency"}, "attributes": "$decimalsMonetary"}, {"code": "dp438169", "dimensions": {"concept": "eba_met:mi776", "eba_dim:BAS": "eba_BA:x17", "eba_dim:CCA": "eba_CA:x2", "eba_dim:TIT": "eba_RP:x65", "eba_dim:TRE": "eba_MC:x916", "unit": "$baseCurrency"}, "attributes": "$decimalsMonetary"}, {"code": "dp438170", "dimensions": {"concept": "eba_met:mi776", "eba_dim:BAS": "eba_BA:x17", "eba_dim:CCA": "eba_CA:x2", "eba_dim:TIT": "eba_RP:x65", "eba_dim:TRE": "eba_MC:x916", "eba_dim:TWR": "eba_RF:x53", "unit": "$baseCurrency"}, "attributes": "$decimalsMonetary"}, {"code": "dp438171", "dimensions": {"concept": "eba_met:mi777", "eba_dim:BAS": "eba_BA:x17", "eba_dim:CCA": "eba_CA:x2", "eba_dim:TIT": "eba_RP:x87", "eba_dim:TRE": "eba_MC:x916", "eba_dim:TWR": "eba_RF:x52", "eba_dim:TYA": "eba_TA:x5", "unit": "$baseCurrency"}, "attributes": "$decimalsMonetary"}, {"code": "dp438172", "dimensions": {"concept": "eba_met:mi777", "eba_dim:BAS": "eba_BA:x17", "eba_dim:CCA": "eba_CA:x2", "eba_dim:TIT": "eba_RP:x87", "eba_dim:TRE": "eba_MC:x916", "eba_dim:TWR": "eba_RF:x52", "eba_dim:TYA": "eba_TA:x29", "unit": "$baseCurrency"}, "attributes": "$decimalsMonetary"}, {"code": "dp438173", "dimensions": {"concept": "eba_met:mi777", "eba_dim:BAS": "eba_BA:x17", "eba_dim:CCA": "eba_CA:x2", "eba_dim:TIT": "eba_RP:x87", "eba_dim:TRE": "eba_MC:x916", "eba_dim:TWR": "eba_RF:x52", "eba_dim:TYA": "eba_TA:x125", "unit": "$baseCurrency"}, "attributes": "$decimalsMonetary"}, {"code": "dp438174", "dimensions": {"concept": "eba_met:mi777", "eba_dim:BAS": "eba_BA:x17", "eba_dim:CCA": "eba_CA:x2", "eba_dim:TIT": "eba_RP:x87", "eba_dim:TRE": "eba_MC:x916", "eba_dim:TWR": "eba_RF:x52", "eba_dim:TYA": "eba_TA:x126", "unit": "$baseCurrency"}, "attributes": "$decimalsMonetary"}, {"code": "dp438175", "dimensions": {"concept": "eba_met:mi777", "eba_dim:BAS": "eba_BA:x17", "eba_dim:CCA": "eba_CA:x2", "eba_dim:TIT": "eba_RP:x87", "eba_dim:TRE": "eba_MC:x916", "eba_dim:TWR": "eba_RF:x52", "eba_dim:TYA": "eba_TA:x127", "unit": "$baseCurrency"}, "attributes": "$decimalsMonetary"}, {"code": "dp438176", "dimensions": {"concept": "eba_met:mi777", "eba_dim:BAS": "eba_BA:x17", "eba_dim:CCA": "eba_CA:x2", "eba_dim:TIT": "eba_RP:x87", "eba_dim:TRE": "eba_MC:x916", "eba_dim:TWR": "eba_RF:x52", "eba_dim:TYA": "eba_TA:x128", "unit": "$baseCurrency"}, "attributes": "$decimalsMonetary"}, {"code": "dp438177", "dimensions": {"concept": "eba_met:mi777", "eba_dim:BAS": "eba_BA:x17", "eba_dim:CCA": "eba_CA:x2", "eba_dim:TIT": "eba_RP:x64", "eba_dim:TRE": "eba_MC:x916", "eba_dim:TWR": "eba_RF:x52", "unit": "$baseCurrency"}, "attributes": "$decimalsMonetary"}, {"code": "dp438178", "dimensions": {"concept": "eba_met:mi777", "eba_dim:BAS": "eba_BA:x17", "eba_dim:CCA": "eba_CA:x2", "eba_dim:TIT": "eba_RP:x65", "eba_dim:TRE": "eba_MC:x916", "eba_dim:TWR": "eba_RF:x52", "unit": "$baseCurrency"}, "attributes": "$decimalsMonetary"}, {"code": "dp459427", "dimensions": {"concept": "eba_met:md103", "eba_dim:BAS": "eba_BA:x17", "eba_dim:CCA": "eba_CA:x2", "eba_dim:TIT": "eba_RP:x64", "eba_dim:TRE": "eba_MC:x916", "unit": "$baseCurrency"}, "attributes": "$decimalsMonetary"}, {"code": "dp459429", "dimensions": {"concept": "eba_met:md103", "eba_dim:BAS": "eba_BA:x17", "eba_dim:CCA": "eba_CA:x2", "eba_dim:TIT": "eba_RP:x65", "eba_dim:TRE": "eba_MC:x916", "unit": "$baseCurrency"}, "attributes": "$decimalsMonetary"}, {"code": "dp459509", "dimensions": {"concept": "eba_met:ii774", "eba_dim:BAS": "eba_BA:x17", "eba_dim:TIT": "eba_RP:x64"}, "attributes": "$decimalsInteger"}, {"code": "dp459510", "dimensions": {"concept": "eba_met:ii774", "eba_dim:BAS": "eba_BA:x17", "eba_dim:TIT": "eba_RP:x65"}, "attributes": "$decimalsInteger"}], "attributes": []}, {"code": "R_02-00-b", "url": "r_02.00.b.csv", "architecture": "datapoints", "open_keys": [], "variables": [{"code": "dp438081", "dimensions": {"concept": "eba_met:ii774", "eba_dim:BAS": "eba_BA:x17", "eba_dim:TIT": "eba_RP:x67", "eba_dim:TYA": "eba_TA:x5"}, "attributes": "$decimalsInteger"}, {"code": "dp438082", "dimensions": {"concept": "eba_met:ii774", "eba_dim:BAS": "eba_BA:x17", "eba_dim:TIT": "eba_RP:x67", "eba_dim:TYA": "eba_TA:x29"}, "attributes": "$decimalsInteger"}, {"code": "dp438083", "dimensions": {"concept": "eba_met:ii774", "eba_dim:BAS": "eba_BA:x17", "eba_dim:TIT": "eba_RP:x67", "eba_dim:TYA": "eba_TA:x125"}, "attributes": "$decimalsInteger"}, {"code": "dp438084", "dimensions": {"concept": "eba_met:ii774", "eba_dim:BAS": "eba_BA:x17", "eba_dim:TIT": "eba_RP:x67", "eba_dim:TYA": "eba_TA:x126"}, "attributes": "$decimalsInteger"}, {"code": "dp438085", "dimensions": {"concept": "eba_met:ii774", "eba_dim:BAS": "eba_BA:x17", "eba_dim:TIT": "eba_RP:x67", "eba_dim:TYA": "eba_TA:x127"}, "attributes": "$decimalsInteger"}, {"code": "dp438086", "dimensions": {"concept": "eba_met:ii774", "eba_dim:BAS": "eba_BA:x17", "eba_dim:TIT": "eba_RP:x67", "eba_dim:TYA": "eba_TA:x128"}, "attributes": "$decimalsInteger"}], "attributes": []}, {"code": "R_03-00", "url": "r_03.00.csv", "architecture": "datapoints", "open_keys": ["PYB"], "variables": [{"code": "dp438078", "dimensions": {"concept": "eba_met:ii774", "eba_dim:BAS": "eba_BA:x17", "eba_dim:TIT": "eba_RP:x63"}, "attributes": "$decimalsInteger"}], "attributes": []}]}